MANIFEST.in
README.txt
setup.py
docs/HISTORY.txt
docs/VERSION.txt
trueaction/__init__.py
trueaction.mongofile.egg-info/PKG-INFO
trueaction.mongofile.egg-info/SOURCES.txt
trueaction.mongofile.egg-info/dependency_links.txt
trueaction.mongofile.egg-info/entry_points.txt
trueaction.mongofile.egg-info/requires.txt
trueaction.mongofile.egg-info/top_level.txt
trueaction.mongofile.egg-info/zip-safe
trueaction/mongofile/__init__.py
trueaction/mongofile/mongo_file.py
trueaction/mongofile/tests.py