Metadata-Version: 1.0
Name: trueaction.mongofile
Version: 0.2.3
Summary: A way to read, write, and append file-like objects to MongoDB
Home-page: http://trueaction.com
Author: Michael A. Smith
Author-email: smithm@trueaction.com
License: http://opensource.org/licenses/academic.php
Keywords: TrueAction Python MongoDB Files
Platform: UNKNOWN
Classifier: Development Status :: 2 - Pre-Alpha
Classifier: Intended Audience :: Developers
Classifier: License :: OSI Approved :: Academic Free License (AFL)
Classifier: Operating System :: OS Independent
Classifier: Programming Language :: Python
Classifier: Topic :: Database
Classifier: Topic :: System :: Filesystems
